negetis/__init__.py
negetis/build.py
negetis/builder.py
negetis/config.py
negetis/extensions.py
negetis/log.py
negetis/main.py
negetis/new.py
negetis/processor.py
negetis/resources/example/.gitignore
negetis/resources/example/config.yaml
negetis/resources/example/content/en/about/company/name.md
negetis/resources/example/content/en/about/index.md
negetis/resources/example/content/en/index.md
negetis/resources/example/content/en/posts/hello-world.md
negetis/resources/example/content/rus/about/index.md
negetis/resources/example/content/rus/about/lang.png
negetis/resources/example/content/rus/about/sub.md
negetis/resources/example/content/rus/index.md
negetis/resources/example/static/en/en.txt
negetis/resources/example/static/en/lang.png
negetis/resources/example/static/ru/lang.png
negetis/resources/example/static/ru/ru.txt
negetis/resources/example/themes/basic/archetypes/post.md
negetis/resources/example/themes/basic/layouts/404.html
negetis/resources/example/themes/basic/layouts/default.html
negetis/resources/example/themes/basic/layouts/index.html
negetis/resources/example/themes/basic/layouts/partials/base.html
negetis/resources/example/themes/basic/layouts/partials/footer.html
negetis/resources/example/themes/basic/layouts/partials/head.html
negetis/resources/example/themes/basic/layouts/partials/header.html
negetis/resources/example/themes/basic/static/img/favicon-16x16.png
negetis/resources/example/themes/basic/static/img/favicon-32x32.png
negetis/resources/example/themes/basic/theme.yaml
negetis/resources/i18n/ru.yaml
negetis/resources/site/config.yaml
negetis/resources/site/content/.placeholder
negetis/resources/site/static/.placeholder
negetis/resources/site/themes/.placeholder
negetis/resources/theme/LICENSE.md
negetis/resources/theme/archetypes/post.md
negetis/resources/theme/layouts/404.html
negetis/resources/theme/layouts/_base/base.html
negetis/resources/theme/layouts/_base/list.html
negetis/resources/theme/layouts/_base/single.html
negetis-0.1.3.dist-info/entry_points.txt
negetis-0.1.3.dist-info/LICENSE
negetis-0.1.3.dist-info/WHEEL
negetis-0.1.3.dist-info/METADATA
negetis-0.1.3.dist-info/RECORD
